images.py
images_py-0.1.2.dist-info/METADATA
images_py-0.1.2.dist-info/WHEEL
images_py-0.1.2.dist-info/RECORD
