Metadata-Version: 2.4
Name: images-py
Version: 0.1.2
Summary: Kenneth Lambert's image processing library (UNOFFICIAL)
Maintainer-email: Aero <aerocyberdev@proton.me>
License-Expression: GPL-3.0-or-later
Requires-Python: >=3.2
